{
  "api_request": {
    "error": {},
    "resources": [
      "document"
    ],
    "status": "success",
    "status_code": 201,
    "url": "https://api.mindee.net/v1/products/mindee/expense_receipts/v5/predict"
  },
  "document": {
    "id": "44d15af2-47d7-4921-92c1-32c06743d3b9",
    "inference": {
      "extras": {},
      "finished_at": "2024-05-15T09:02:58.822600",
      "is_rotation_applied": true,
      "pages": [
        {
          "extras": {},
          "id": 0,
          "orientation": {
            "value": 0
          },
          "prediction": {
            "category": {
              "confidence": 0.99,
              "value": "food"
            },
            "date": {
              "confidence": 0.99,
              "polygon": [
                [
                  0.475,
                  0.173
                ],
                [
                  0.61,
                  0.173
                ],
                [
                  0.61,
                  0.195
                ],
                [
                  0.475,
                  0.195
                ]
              ],
              "value": "2016-02-26"
            },
            "document_type": {
              "confidence": 1.0,
              "value": "EXPENSE RECEIPT"
            },
            "line_items": [
              {
                "confidence": 0.97,
                "description": "Meantime Pale",
                "polygon": [
                  [
                    0.235,
                    0.268
                  ],
                  [
                    0.686,
                    0.261
                  ],
                  [
                    0.687,
                    0.285
                  ],
                  [
                    0.236,
                    0.293
                  ]
                ],
                "quantity": 2.0,
                "total_amount": 10.2,
                "unit_price": null
              }
            ],
            "locale": {
              "confidence": 0.82,
              "country": "GB",
              "currency": "GBP",
              "language": "en",
              "value": "en-GB"
            },
            "orientation": {
              "confidence": 0.99,
              "degrees": 0
            },
            "receipt_number": {
              "confidence": 0.99,
              "polygon": [
                [
                  0.329,
                  0.678
                ],
                [
                  0.428,
                  0.678
                ],
                [
                  0.428,
                  0.705
                ],
                [
                  0.329,
                  0.705
                ]
              ],
              "value": "54/7500"
            },
            "subcategory": {
              "confidence": 0.99,
              "value": "restaurant"
            },
            "supplier_address": {
              "confidence": 0.87,
              "polygon": [
                [
                  0.34,
                  0.086
                ],
                [
                  0.532,
                  0.086
                ],
                [
                  0.532,
                  0.131
                ],
                [
                  0.34,
                  0.131
                ]
              ],
              "value": "34 kingley street w1b 5qh"
            },
            "supplier_company_registrations": [
              {
                "confidence": 0.95,
                "polygon": [
                  [
                    0.375,
                    0.941
                  ],
                  [
                    0.548,
                    0.941
                  ],
                  [
                    0.548,
                    0.971
                  ],
                  [
                    0.375,
                    0.971
                  ]
                ],
                "type": "VAT NUMBER",
                "value": "232153895"
              },
              {
                "confidence": 0.98,
                "polygon": [
                  [
                    0.215,
                    0.71
                  ],
                  [
                    0.374,
                    0.71
                  ],
                  [
                    0.374,
                    0.736
                  ],
                  [
                    0.215,
                    0.736
                  ]
                ],
                "type": "VAT NUMBER",
                "value": "232153895"
              }
            ],
            "supplier_name": {
              "confidence": 0.96,
              "polygon": [
                [
                  0.395,
                  0.067
                ],
                [
                  0.475,
                  0.067
                ],
                [
                  0.475,
                  0.088
                ],
                [
                  0.395,
                  0.088
                ]
              ],
              "raw_value": "Clachan",
              "value": "Clachan"
            },
            "supplier_phone_number": {
              "confidence": 0.39,
              "polygon": [
                [
                  0.371,
                  0.905
                ],
                [
                  0.575,
                  0.905
                ],
                [
                  0.575,
                  0.936
                ],
                [
                  0.371,
                  0.936
                ]
              ],
              "value": "02074940834"
            },
            "taxes": [
              {
                "base": 8.5,
                "code": "VAT",
                "confidence": 0.99,
                "polygon": [
                  [
                    0.17,
                    0.647
                  ],
                  [
                    0.719,
                    0.647
                  ],
                  [
                    0.719,
                    0.675
                  ],
                  [
                    0.17,
                    0.675
                  ]
                ],
                "rate": 20.0,
                "value": 1.7
              }
            ],
            "time": {
              "confidence": 0.99,
              "polygon": [
                [
                  0.619,
                  0.172
                ],
                [
                  0.679,
                  0.172
                ],
                [
                  0.679,
                  0.19
                ],
                [
                  0.619,
                  0.19
                ]
              ],
              "value": "15:20"
            },
            "tip": {
              "confidence": 0.0,
              "polygon": [],
              "value": null
            },
            "total_amount": {
              "confidence": 0.99,
              "polygon": [
                [
                  0.549,
                  0.619
                ],
                [
                  0.715,
                  0.619
                ],
                [
                  0.715,
                  0.642
                ],
                [
                  0.549,
                  0.642
                ]
              ],
              "value": 10.2
            },
            "total_net": {
              "confidence": 0.99,
              "polygon": [
                [
                  0.641,
                  0.38
                ],
                [
                  0.695,
                  0.38
                ],
                [
                  0.695,
                  0.399
                ],
                [
                  0.641,
                  0.399
                ]
              ],
              "value": 8.5
            },
            "total_tax": {
              "confidence": 0.99,
              "polygon": [],
              "value": 1.7
            }
          }
        }
      ],
      "prediction": {
        "category": {
          "confidence": 0.99,
          "value": "food"
        },
        "date": {
          "confidence": 0.99,
          "page_id": 0,
          "polygon": [
            [
              0.475,
              0.173
            ],
            [
              0.61,
              0.173
            ],
            [
              0.61,
              0.195
            ],
            [
              0.475,
              0.195
            ]
          ],
          "value": "2016-02-26"
        },
        "document_type": {
          "confidence": 1.0,
          "value": "EXPENSE RECEIPT"
        },
        "line_items": [
          {
            "confidence": 0.97,
            "description": "Meantime Pale",
            "page_id": 0,
            "polygon": [
              [
                0.235,
                0.268
              ],
              [
                0.686,
                0.261
              ],
              [
                0.687,
                0.285
              ],
              [
                0.236,
                0.293
              ]
            ],
            "quantity": 2.0,
            "total_amount": 10.2,
            "unit_price": null
          }
        ],
        "locale": {
          "confidence": 0.82,
          "country": "GB",
          "currency": "GBP",
          "language": "en",
          "value": "en-GB"
        },
        "receipt_number": {
          "confidence": 0.99,
          "page_id": 0,
          "polygon": [
            [
              0.329,
              0.678
            ],
            [
              0.428,
              0.678
            ],
            [
              0.428,
              0.705
            ],
            [
              0.329,
              0.705
            ]
          ],
          "value": "54/7500"
        },
        "subcategory": {
          "confidence": 0.99,
          "value": "restaurant"
        },
        "supplier_address": {
          "confidence": 0.87,
          "page_id": 0,
          "polygon": [
            [
              0.34,
              0.086
            ],
            [
              0.532,
              0.086
            ],
            [
              0.532,
              0.131
            ],
            [
              0.34,
              0.131
            ]
          ],
          "value": "34 kingley street w1b 5qh"
        },
        "supplier_company_registrations": [
          {
            "confidence": 0.95,
            "page_id": 0,
            "polygon": [
              [
                0.375,
                0.941
              ],
              [
                0.548,
                0.941
              ],
              [
                0.548,
                0.971
              ],
              [
                0.375,
                0.971
              ]
            ],
            "type": "VAT NUMBER",
            "value": "232153895"
          },
          {
            "confidence": 0.98,
            "page_id": 0,
            "polygon": [
              [
                0.215,
                0.71
              ],
              [
                0.374,
                0.71
              ],
              [
                0.374,
                0.736
              ],
              [
                0.215,
                0.736
              ]
            ],
            "type": "VAT NUMBER",
            "value": "232153895"
          }
        ],
        "supplier_name": {
          "confidence": 0.96,
          "page_id": 0,
          "polygon": [
            [
              0.395,
              0.067
            ],
            [
              0.475,
              0.067
            ],
            [
              0.475,
              0.088
            ],
            [
              0.395,
              0.088
            ]
          ],
          "raw_value": "Clachan",
          "value": "Clachan"
        },
        "supplier_phone_number": {
          "confidence": 0.39,
          "page_id": 0,
          "polygon": [
            [
              0.371,
              0.905
            ],
            [
              0.575,
              0.905
            ],
            [
              0.575,
              0.936
            ],
            [
              0.371,
              0.936
            ]
          ],
          "value": "02074940834"
        },
        "taxes": [
          {
            "base": 8.5,
            "code": "VAT",
            "confidence": 0.99,
            "page_id": 0,
            "polygon": [
              [
                0.17,
                0.647
              ],
              [
                0.719,
                0.647
              ],
              [
                0.719,
                0.675
              ],
              [
                0.17,
                0.675
              ]
            ],
            "rate": 20.0,
            "value": 1.7
          }
        ],
        "time": {
          "confidence": 0.99,
          "page_id": 0,
          "polygon": [
            [
              0.619,
              0.172
            ],
            [
              0.679,
              0.172
            ],
            [
              0.679,
              0.19
            ],
            [
              0.619,
              0.19
            ]
          ],
          "value": "15:20"
        },
        "tip": {
          "confidence": 0.0,
          "page_id": null,
          "polygon": [],
          "value": null
        },
        "total_amount": {
          "confidence": 0.99,
          "page_id": 0,
          "polygon": [
            [
              0.549,
              0.619
            ],
            [
              0.715,
              0.619
            ],
            [
              0.715,
              0.642
            ],
            [
              0.549,
              0.642
            ]
          ],
          "value": 10.2
        },
        "total_net": {
          "confidence": 0.99,
          "page_id": 0,
          "polygon": [
            [
              0.641,
              0.38
            ],
            [
              0.695,
              0.38
            ],
            [
              0.695,
              0.399
            ],
            [
              0.641,
              0.399
            ]
          ],
          "value": 8.5
        },
        "total_tax": {
          "confidence": 0.99,
          "page_id": null,
          "polygon": [],
          "value": 1.7
        }
      },
      "processing_time": 1.18,
      "product": {
        "features": [
          "locale",
          "category",
          "subcategory",
          "document_type",
          "date",
          "time",
          "total_amount",
          "total_net",
          "total_tax",
          "tip",
          "taxes",
          "supplier_name",
          "supplier_company_registrations",
          "supplier_address",
          "supplier_phone_number",
          "orientation",
          "receipt_number",
          "line_items"
        ],
        "name": "mindee/expense_receipts",
        "type": "standard",
        "version": "5.2"
      },
      "started_at": "2024-05-15T09:02:57.642819"
    },
    "n_pages": 1,
    "name": "default_sample.jpg"
  }
}
